pysqlified/__init__.py
pysqlified/py.typed
pysqlified-0.1.0.dist-info/METADATA
pysqlified-0.1.0.dist-info/WHEEL
pysqlified-0.1.0.dist-info/licenses/LICENSE
pysqlified-0.1.0.dist-info/RECORD
