Metadata-Version: 2.4
Name: pysqlified
Version: 0.1.0
Summary: Add your description here
Author-email: alexeev-prog <alexeev.dev@mail.ru>
License-File: LICENSE
Requires-Python: >=3.9
Requires-Dist: asyncio>=3.4.3
Requires-Dist: requests>=2.32.3
Requires-Dist: rich>=13.9.4
Requires-Dist: tqdm>=4.67.1
